picombo/__init__.py
picombo/pick.py
picombo-1.0.2.dist-info/LICENSE
picombo-1.0.2.dist-info/METADATA
picombo-1.0.2.dist-info/WHEEL
picombo-1.0.2.dist-info/top_level.txt
picombo-1.0.2.dist-info/RECORD
