Metadata-Version: 2.1
Name: picombo
Version: 1.0.2
Summary: Users select an item from a list and retrieve it.
Author-email: Udon Asakawa <udonuopn.a@gmail.com>
License: MIT License
Project-URL: homepage, https://github.com/udonuopn/picombo
Classifier: Programming Language :: Python :: 3
Classifier: License :: OSI Approved :: MIT License
Requires-Python: >=3.6
License-File: LICENSE
Requires-Dist: prompt-toolkit
